train_time/__init__.py
train_time/traintime.py
train_time-0.1.5.dist-info/LICENSE
train_time-0.1.5.dist-info/METADATA
train_time-0.1.5.dist-info/WHEEL
train_time-0.1.5.dist-info/top_level.txt
train_time-0.1.5.dist-info/RECORD
