Metadata-Version: 2.1
Name: train-time
Version: 0.1.5
Summary: A Keras callback to estimate remaining training time
Home-page: https://github.com/2abet/TrainTime
Author: Akinyemi Arabambi
License-File: LICENSE
Requires-Dist: keras
